{
  "phase": "06-version-monitoring",
  "plan": "04",
  "status": "complete",
  "started_at": "2026-02-21T08:38:26Z",
  "completed_at": "2026-02-21T08:42:20Z",
  "duration_seconds": 234,
  "tasks": [
    {
      "task": 1,
      "name": "Enhance /v1/schema/versions and /v1/schema/drift API handlers",
      "status": "complete",
      "commit": "1cc4132",
      "files_modified": [
        "crates/server/src/api/schema.rs"
      ]
    },
    {
      "task": 2,
      "name": "Enhance CLI version-check and schema-drift subcommands",
      "status": "complete",
      "commit": "d6c646a",
      "files_modified": [
        "crates/server/src/main.rs",
        "crates/server/src/output.rs",
        "crates/server/src/daemon_client.rs"
      ]
    }
  ],
  "deviations": [],
  "verification": {
    "cargo_check": "pass",
    "cargo_test": "pass",
    "cargo_build": "pass",
    "test_count": {
      "core": 38,
      "store": 110,
      "total": 148
    }
  },
  "requirements_completed": ["VER-01", "VER-02", "VER-03"]
}
